<?xml version="1.0" encoding="UTF-8"?>
<!DOCTYPE suite SYSTEM "https://testng.org/testng-1.0.dtd">
<suite name="Suite" parallel="tests" thread-count="5">
  <parameter name="browser"  value="Chrome" />
  <test name="OrangeHRM">
    <classes>
      <class name="testcases.TC_00_LoginOrangeHRM"/>
    </classes>
  </test>
  <test name="DemoWebShop">
    <classes>
   	  <class name="testcases.TC_05_DemoWebShop_Register"/>
   	  <class name="testcases.TC_07_DemoWebShop_PlaceOrder"/>
   	  <class name="testcases.TC_08_ReOrder"/>
   	  <class name="testcases.TC_09_AllOrdersTotal"/>
    </classes>
  </test> 
  
</suite> <!-- Suite -->

